goodreadsscraper/__init__.py
goodreadsscraper/author.py
goodreadsscraper/book.py
goodreadsscraper/review.py
goodreadsscraper/utils.py
goodreadsscraper/test/debug.html
goodreadsscraper-0.4.dist-info/entry_points.txt
goodreadsscraper-0.4.dist-info/LICENSE
goodreadsscraper-0.4.dist-info/WHEEL
goodreadsscraper-0.4.dist-info/METADATA
goodreadsscraper-0.4.dist-info/RECORD
