Metadata-Version: 2.1
Name: goodreadsscraper
Version: 0.4
Summary: Module to scrap book information from goodreads
Author-email: brazafonso <a93178@uminho.pt>, Tiago Silva <a93277@uminho.pt>
Classifier: License :: OSI Approved :: MIT License
Requires-Dist: jellyfish
Requires-Dist: pandas
Requires-Dist: bs4
Requires-Dist: selenium
Requires-Dist: argparse
